{"lastUsed":1584467816676,"path":"E:\/Eclipse code","projectCount":1,"recentFiles":[{"path":"\/gerenciador\/WebContent","parentWorkspace":"E:\/Eclipse code","name":"formNovaEmpresa.html","lastModified":1584465762843,"locationURI":"file:\/E:\/Eclipse%20code\/gerenciador\/WebContent\/formNovaEmpresa.html"},{"path":"\/gerenciador\/src\/br\/com\/alura\/gerenciador\/servlet","parentWorkspace":"E:\/Eclipse code","name":"OiMundoServlet.java","lastModified":1584461842704,"locationURI":"file:\/E:\/Eclipse%20code\/gerenciador\/src\/br\/com\/alura\/gerenciador\/servlet\/OiMundoServlet.java"},{"path":"\/gerenciador\/src\/br\/com\/alura\/gerenciador\/servlet","parentWorkspace":"E:\/Eclipse code","name":"NovaEmpresaServlet.java","lastModified":1584467816677,"locationURI":"file:\/E:\/Eclipse%20code\/gerenciador\/src\/br\/com\/alura\/gerenciador\/servlet\/NovaEmpresaServlet.java"},{"path":"\/gerenciador\/WebContent","parentWorkspace":"E:\/Eclipse code","name":"bem-vindo.html","lastModified":1584385593349,"locationURI":"file:\/E:\/Eclipse%20code\/gerenciador\/WebContent\/bem-vindo.html"}]}